[
    {
        "status": 400,
        "message": "Title must be between 4 and 100 characters"
    },
    {
        "status": 400,
        "message": "Title must be between 4 and 100 characters"
    },
    {
        "status": 400,
        "message": "Title must be between 4 and 100 characters"
    },
    {
        "status": 400,
        "message": "Description must be between 4 and 1000 characters"
    },
    {
        "status": 400,
        "message": "Category must be one of the categories: Home, Work, Personal"
    },
    {
        "status": 200,
        "message": "Note successfully created"
    }
]